<?xml version="1.0"?>
<!--
This is a description of the auto-generated fault tree
with the following parameters:

The fault tree name: Autogenerated-BE-with-both-Low-and-High-Probability
The root gate name: root

The seed of the random number generator: 123
The number of basic events: 100
The number of house events: 0.0
The number of CCF groups: 0
The average number of gate arguments: 3.0
The weights of gate types [AND, OR, K/N, NOT, XOR]: [1.0, 1.0, 1.0, 0.0, 0.0]
Percentage of common basic events per gate: 0.3
Percentage of common gates per gate: 0.1
The avg. number of parents for common basic events: 2
The avg. number of parents for common gates: 2
Maximum probability for basic events: 0.9
Minimum probability for basic events: 0.01
-->
<!--
The generated fault tree has the following metrics:

The number of basic events: 100
The number of house events: 0
The number of CCF groups: 0
The number of gates: 57
    AND gates: 19
    OR gates: 17
    K/N gates: 21
    NOT gates: 0
    XOR gates: 0
Basic events to gates ratio: 1.7543859649122806
The average number of gate arguments: 3.0
The number of common basic events: 14
The number of common gates: 1
Percentage of common basic events per gate: 0.22878787878787876
Percentage of common gates per gate: 0.038461538461538464
Percentage of arguments that are basic events per gate: 0.6695906432748538
The avg. number of parents for common basic events: 2.0
The avg. number of parents for common gates: 2.0
-->

<opsa-mef>
<define-fault-tree name="Autogenerated-BE-with-both-Low-and-High-Probability">
<define-gate name="root">
<and>
<basic-event name="B18"/>
<gate name="G5"/>
</and>
</define-gate>
<define-gate name="G5">
<and>
<basic-event name="B19"/>
<gate name="G6"/>
<gate name="G7"/>
</and>
</define-gate>
<define-gate name="G7">
<atleast min="2">
<basic-event name="B23"/>
<gate name="G2"/>
<gate name="G8"/>
</atleast>
</define-gate>
<define-gate name="G8">
<and>
<basic-event name="B25"/>
<basic-event name="B10"/>
<basic-event name="B24"/>
</and>
</define-gate>
<define-gate name="G2">
<and>
<basic-event name="B9"/>
<basic-event name="B26"/>
<gate name="G9"/>
</and>
</define-gate>
<define-gate name="G9">
<and>
<basic-event name="B27"/>
<basic-event name="B28"/>
<gate name="G10"/>
</and>
</define-gate>
<define-gate name="G10">
<atleast min="2">
<basic-event name="B8"/>
<basic-event name="B14"/>
<gate name="G12"/>
<gate name="G11"/>
</atleast>
</define-gate>
<define-gate name="G11">
<or>
<basic-event name="B30"/>
<basic-event name="B31"/>
<basic-event name="B29"/>
<gate name="G4"/>
</or>
</define-gate>
<define-gate name="G4">
<atleast min="3">
<basic-event name="B33"/>
<gate name="G15"/>
<gate name="G14"/>
<gate name="G16"/>
</atleast>
</define-gate>
<define-gate name="G16">
<and>
<basic-event name="B37"/>
<basic-event name="B38"/>
<gate name="G19"/>
</and>
</define-gate>
<define-gate name="G19">
<atleast min="2">
<basic-event name="B43"/>
<basic-event name="B7"/>
<basic-event name="B42"/>
<gate name="G3"/>
</atleast>
</define-gate>
<define-gate name="G14">
<or>
<basic-event name="B11"/>
<basic-event name="B35"/>
<gate name="G17"/>
</or>
</define-gate>
<define-gate name="G17">
<and>
<basic-event name="B2"/>
<basic-event name="B39"/>
</and>
</define-gate>
<define-gate name="G15">
<atleast min="2">
<basic-event name="B36"/>
<basic-event name="B15"/>
<gate name="G22"/>
<gate name="G18"/>
</atleast>
</define-gate>
<define-gate name="G18">
<atleast min="2">
<basic-event name="B40"/>
<basic-event name="B41"/>
<gate name="G20"/>
</atleast>
</define-gate>
<define-gate name="G20">
<atleast min="3">
<basic-event name="B45"/>
<basic-event name="B6"/>
<basic-event name="B44"/>
<basic-event name="B3"/>
</atleast>
</define-gate>
<define-gate name="G22">
<and>
<basic-event name="B49"/>
<gate name="G23"/>
</and>
</define-gate>
<define-gate name="G23">
<and>
<basic-event name="B51"/>
<basic-event name="B50"/>
<gate name="G24"/>
</and>
</define-gate>
<define-gate name="G24">
<atleast min="2">
<basic-event name="B12"/>
<gate name="G26"/>
<gate name="G25"/>
</atleast>
</define-gate>
<define-gate name="G25">
<or>
<basic-event name="B53"/>
<basic-event name="B52"/>
<gate name="G27"/>
</or>
</define-gate>
<define-gate name="G27">
<and>
<basic-event name="B56"/>
<gate name="G30"/>
<gate name="G3"/>
</and>
</define-gate>
<define-gate name="G3">
<or>
<basic-event name="B13"/>
<basic-event name="B46"/>
<basic-event name="B4"/>
</or>
</define-gate>
<define-gate name="G30">
<and>
<gate name="G37"/>
<gate name="G36"/>
</and>
</define-gate>
<define-gate name="G36">
<or>
<basic-event name="B66"/>
<basic-event name="B67"/>
</or>
</define-gate>
<define-gate name="G37">
<and>
<basic-event name="B68"/>
<gate name="G42"/>
</and>
</define-gate>
<define-gate name="G42">
<or>
<basic-event name="B1"/>
<basic-event name="B75"/>
</or>
</define-gate>
<define-gate name="G26">
<atleast min="2">
<basic-event name="B55"/>
<basic-event name="B54"/>
<gate name="G29"/>
<gate name="G28"/>
</atleast>
</define-gate>
<define-gate name="G28">
<atleast min="2">
<gate name="G31"/>
<gate name="G33"/>
<gate name="G32"/>
</atleast>
</define-gate>
<define-gate name="G32">
<and>
<basic-event name="B60"/>
<gate name="G38"/>
</and>
</define-gate>
<define-gate name="G38">
<and>
<basic-event name="B5"/>
<basic-event name="B69"/>
<gate name="G43"/>
</and>
</define-gate>
<define-gate name="G43">
<atleast min="2">
<basic-event name="B77"/>
<basic-event name="B78"/>
<basic-event name="B76"/>
</atleast>
</define-gate>
<define-gate name="G33">
<or>
<basic-event name="B62"/>
<basic-event name="B61"/>
</or>
</define-gate>
<define-gate name="G31">
<atleast min="2">
<basic-event name="B58"/>
<basic-event name="B59"/>
<basic-event name="B14"/>
</atleast>
</define-gate>
<define-gate name="G29">
<atleast min="2">
<basic-event name="B57"/>
<gate name="G35"/>
<gate name="G34"/>
</atleast>
</define-gate>
<define-gate name="G34">
<atleast min="2">
<basic-event name="B64"/>
<basic-event name="B63"/>
<gate name="G39"/>
</atleast>
</define-gate>
<define-gate name="G39">
<atleast min="3">
<basic-event name="B70"/>
<basic-event name="B71"/>
<gate name="G44"/>
<gate name="G45"/>
</atleast>
</define-gate>
<define-gate name="G45">
<atleast min="2">
<basic-event name="B81"/>
<basic-event name="B80"/>
<basic-event name="B82"/>
</atleast>
</define-gate>
<define-gate name="G44">
<atleast min="2">
<basic-event name="B9"/>
<basic-event name="B79"/>
<gate name="G47"/>
</atleast>
</define-gate>
<define-gate name="G47">
<and>
<basic-event name="B85"/>
<gate name="G49"/>
</and>
</define-gate>
<define-gate name="G49">
<or>
<basic-event name="B87"/>
<basic-event name="B88"/>
<gate name="G51"/>
</or>
</define-gate>
<define-gate name="G51">
<or>
<basic-event name="B90"/>
<basic-event name="B91"/>
</or>
</define-gate>
<define-gate name="G35">
<atleast min="2">
<basic-event name="B65"/>
<gate name="G41"/>
<gate name="G40"/>
</atleast>
</define-gate>
<define-gate name="G40">
<or>
<basic-event name="B12"/>
<basic-event name="B72"/>
<gate name="G46"/>
</or>
</define-gate>
<define-gate name="G46">
<or>
<basic-event name="B83"/>
<basic-event name="B84"/>
<gate name="G48"/>
</or>
</define-gate>
<define-gate name="G48">
<atleast min="2">
<basic-event name="B86"/>
<basic-event name="B11"/>
<gate name="G50"/>
</atleast>
</define-gate>
<define-gate name="G50">
<and>
<basic-event name="B2"/>
<basic-event name="B15"/>
<basic-event name="B89"/>
<gate name="G52"/>
</and>
</define-gate>
<define-gate name="G52">
<and>
<basic-event name="B92"/>
<basic-event name="B93"/>
<gate name="G54"/>
<gate name="G53"/>
</and>
</define-gate>
<define-gate name="G53">
<or>
<basic-event name="B94"/>
<basic-event name="B95"/>
<basic-event name="B96"/>
<basic-event name="B97"/>
</or>
</define-gate>
<define-gate name="G54">
<or>
<basic-event name="B6"/>
<gate name="G56"/>
<gate name="G55"/>
</or>
</define-gate>
<define-gate name="G55">
<or>
<basic-event name="B8"/>
<basic-event name="B98"/>
<basic-event name="B4"/>
</or>
</define-gate>
<define-gate name="G56">
<or>
<basic-event name="B99"/>
<basic-event name="B3"/>
<gate name="G57"/>
</or>
</define-gate>
<define-gate name="G57">
<or>
<basic-event name="B100"/>
<basic-event name="B16"/>
</or>
</define-gate>
<define-gate name="G41">
<atleast min="2">
<basic-event name="B17"/>
<basic-event name="B74"/>
<basic-event name="B73"/>
</atleast>
</define-gate>
<define-gate name="G12">
<and>
<basic-event name="B32"/>
<gate name="G21"/>
<gate name="G13"/>
</and>
</define-gate>
<define-gate name="G13">
<atleast min="2">
<basic-event name="B1"/>
<basic-event name="B34"/>
<basic-event name="B5"/>
</atleast>
</define-gate>
<define-gate name="G21">
<or>
<basic-event name="B17"/>
<basic-event name="B48"/>
<basic-event name="B47"/>
</or>
</define-gate>
<define-gate name="G6">
<and>
<basic-event name="B21"/>
<basic-event name="B16"/>
<basic-event name="B20"/>
<basic-event name="B22"/>
</and>
</define-gate>
</define-fault-tree>
<model-data>
<define-basic-event name="B1">
<float value="0.08759614299514276"/>
</define-basic-event>
<define-basic-event name="B2">
<float value="0.37244516966665453"/>
</define-basic-event>
<define-basic-event name="B3">
<float value="0.10585320909521076"/>
</define-basic-event>
<define-basic-event name="B4">
<float value="0.8120670013770083"/>
</define-basic-event>
<define-basic-event name="B5">
<float value="0.04395676283106694"/>
</define-basic-event>
<define-basic-event name="B6">
<float value="0.48721981563019495"/>
</define-basic-event>
<define-basic-event name="B7">
<float value="0.3056559516736151"/>
</define-basic-event>
<define-basic-event name="B8">
<float value="0.7683570908471381"/>
</define-basic-event>
<define-basic-event name="B9">
<float value="0.15209953308255322"/>
</define-basic-event>
<define-basic-event name="B10">
<float value="0.31012282482725523"/>
</define-basic-event>
<define-basic-event name="B11">
<float value="0.3070787912197702"/>
</define-basic-event>
<define-basic-event name="B12">
<float value="0.2281953837406739"/>
</define-basic-event>
<define-basic-event name="B13">
<float value="0.011486792685508342"/>
</define-basic-event>
<define-basic-event name="B14">
<float value="0.39828545613954436"/>
</define-basic-event>
<define-basic-event name="B15">
<float value="0.08797601477787635"/>
</define-basic-event>
<define-basic-event name="B16">
<float value="0.5418635233943115"/>
</define-basic-event>
<define-basic-event name="B17">
<float value="0.07219049569867236"/>
</define-basic-event>
<define-basic-event name="B18">
<float value="0.4276704822903536"/>
</define-basic-event>
<define-basic-event name="B19">
<float value="0.7303112869329863"/>
</define-basic-event>
<define-basic-event name="B20">
<float value="0.5408890590979734"/>
</define-basic-event>
<define-basic-event name="B21">
<float value="0.3833516611406524"/>
</define-basic-event>
<define-basic-event name="B22">
<float value="0.5844517044835074"/>
</define-basic-event>
<define-basic-event name="B23">
<float value="0.30913442838575234"/>
</define-basic-event>
<define-basic-event name="B24">
<float value="0.4558967901323764"/>
</define-basic-event>
<define-basic-event name="B25">
<float value="0.5706917316545786"/>
</define-basic-event>
<define-basic-event name="B26">
<float value="0.0492755718457351"/>
</define-basic-event>
<define-basic-event name="B27">
<float value="0.010316247170213849"/>
</define-basic-event>
<define-basic-event name="B28">
<float value="0.6392767446415284"/>
</define-basic-event>
<define-basic-event name="B29">
<float value="0.28248574562418394"/>
</define-basic-event>
<define-basic-event name="B30">
<float value="0.26916344039707135"/>
</define-basic-event>
<define-basic-event name="B31">
<float value="0.486079290119464"/>
</define-basic-event>
<define-basic-event name="B32">
<float value="0.3537590849745438"/>
</define-basic-event>
<define-basic-event name="B33">
<float value="0.15113390046518882"/>
</define-basic-event>
<define-basic-event name="B34">
<float value="0.8030485601188223"/>
</define-basic-event>
<define-basic-event name="B35">
<float value="0.13054692938634188"/>
</define-basic-event>
<define-basic-event name="B36">
<float value="0.015304965223809568"/>
</define-basic-event>
<define-basic-event name="B37">
<float value="0.8623381502580872"/>
</define-basic-event>
<define-basic-event name="B38">
<float value="0.20276895966793976"/>
</define-basic-event>
<define-basic-event name="B39">
<float value="0.2462765130261211"/>
</define-basic-event>
<define-basic-event name="B40">
<float value="0.05887130245832156"/>
</define-basic-event>
<define-basic-event name="B41">
<float value="0.27567756113145236"/>
</define-basic-event>
<define-basic-event name="B42">
<float value="0.8544215784558412"/>
</define-basic-event>
<define-basic-event name="B43">
<float value="0.8314934892562698"/>
</define-basic-event>
<define-basic-event name="B44">
<float value="0.04805646247099394"/>
</define-basic-event>
<define-basic-event name="B45">
<float value="0.7998958346637932"/>
</define-basic-event>
<define-basic-event name="B46">
<float value="0.02240475122149873"/>
</define-basic-event>
<define-basic-event name="B47">
<float value="0.8349355721682017"/>
</define-basic-event>
<define-basic-event name="B48">
<float value="0.7804491863390318"/>
</define-basic-event>
<define-basic-event name="B49">
<float value="0.2585764388633024"/>
</define-basic-event>
<define-basic-event name="B50">
<float value="0.06353519243975578"/>
</define-basic-event>
<define-basic-event name="B51">
<float value="0.4703894185070317"/>
</define-basic-event>
<define-basic-event name="B52">
<float value="0.28072432853520174"/>
</define-basic-event>
<define-basic-event name="B53">
<float value="0.7096084250961129"/>
</define-basic-event>
<define-basic-event name="B54">
<float value="0.35769940174245884"/>
</define-basic-event>
<define-basic-event name="B55">
<float value="0.4060778407273911"/>
</define-basic-event>
<define-basic-event name="B56">
<float value="0.5376126258175616"/>
</define-basic-event>
<define-basic-event name="B57">
<float value="0.7370474336507623"/>
</define-basic-event>
<define-basic-event name="B58">
<float value="0.5041107844359646"/>
</define-basic-event>
<define-basic-event name="B59">
<float value="0.3213712157978972"/>
</define-basic-event>
<define-basic-event name="B60">
<float value="0.01258000027744165"/>
</define-basic-event>
<define-basic-event name="B61">
<float value="0.48530245473135747"/>
</define-basic-event>
<define-basic-event name="B62">
<float value="0.18059508795108536"/>
</define-basic-event>
<define-basic-event name="B63">
<float value="0.6084947034240246"/>
</define-basic-event>
<define-basic-event name="B64">
<float value="0.09972385727897774"/>
</define-basic-event>
<define-basic-event name="B65">
<float value="0.2343438895461368"/>
</define-basic-event>
<define-basic-event name="B66">
<float value="0.7213302036590935"/>
</define-basic-event>
<define-basic-event name="B67">
<float value="0.5955732532179864"/>
</define-basic-event>
<define-basic-event name="B68">
<float value="0.3555490708178207"/>
</define-basic-event>
<define-basic-event name="B69">
<float value="0.2235843255745606"/>
</define-basic-event>
<define-basic-event name="B70">
<float value="0.28715135188197577"/>
</define-basic-event>
<define-basic-event name="B71">
<float value="0.8938284465683114"/>
</define-basic-event>
<define-basic-event name="B72">
<float value="0.7808303035143802"/>
</define-basic-event>
<define-basic-event name="B73">
<float value="0.3666396568470907"/>
</define-basic-event>
<define-basic-event name="B74">
<float value="0.642915544554374"/>
</define-basic-event>
<define-basic-event name="B75">
<float value="0.8339776076167701"/>
</define-basic-event>
<define-basic-event name="B76">
<float value="0.7958275326380375"/>
</define-basic-event>
<define-basic-event name="B77">
<float value="0.17237196037322675"/>
</define-basic-event>
<define-basic-event name="B78">
<float value="0.5956878661772655"/>
</define-basic-event>
<define-basic-event name="B79">
<float value="0.3346638527065136"/>
</define-basic-event>
<define-basic-event name="B80">
<float value="0.13818305397460307"/>
</define-basic-event>
<define-basic-event name="B81">
<float value="0.5445533669740458"/>
</define-basic-event>
<define-basic-event name="B82">
<float value="0.5679597068630632"/>
</define-basic-event>
<define-basic-event name="B83">
<float value="0.7518127404843983"/>
</define-basic-event>
<define-basic-event name="B84">
<float value="0.5905075044157049"/>
</define-basic-event>
<define-basic-event name="B85">
<float value="0.38502374023448876"/>
</define-basic-event>
<define-basic-event name="B86">
<float value="0.7928450747441588"/>
</define-basic-event>
<define-basic-event name="B87">
<float value="0.689451569819804"/>
</define-basic-event>
<define-basic-event name="B88">
<float value="0.43799066079441734"/>
</define-basic-event>
<define-basic-event name="B89">
<float value="0.16915680666669017"/>
</define-basic-event>
<define-basic-event name="B90">
<float value="0.6970451272638993"/>
</define-basic-event>
<define-basic-event name="B91">
<float value="0.4288315223800555"/>
</define-basic-event>
<define-basic-event name="B92">
<float value="0.06953079767465932"/>
</define-basic-event>
<define-basic-event name="B93">
<float value="0.36271524707627506"/>
</define-basic-event>
<define-basic-event name="B94">
<float value="0.702697301522644"/>
</define-basic-event>
<define-basic-event name="B95">
<float value="0.6092947737896416"/>
</define-basic-event>
<define-basic-event name="B96">
<float value="0.7417376601982901"/>
</define-basic-event>
<define-basic-event name="B97">
<float value="0.039068528520630724"/>
</define-basic-event>
<define-basic-event name="B98">
<float value="0.4546058793147053"/>
</define-basic-event>
<define-basic-event name="B99">
<float value="0.10123597483636497"/>
</define-basic-event>
<define-basic-event name="B100">
<float value="0.8300970248070545"/>
</define-basic-event>
</model-data>
</opsa-mef>
